[
    {
      "id": 1,
      "first_name": "Terra",
      "last_name": "Howes",
      "phone": "250-281-6759",
      "email": "thowes0@businessweek.com",
      "password": "qzwoyeu",
      "active": false
    },
    {
      "id": 2,
      "first_name": "El",
      "last_name": "Kinchin",
      "phone": "248-739-8012",
      "email": "ekinchin1@t-online.de",
      "password": "P8R1TFk",
      "active": false
    },
    {
      "id": 3,
      "first_name": "Cristi",
      "last_name": "Grice",
      "phone": "775-724-1373",
      "email": "cgrice2@earthlink.net",
      "password": "xi2uGWgdw",
      "active": true
    },
    {
      "id": 4,
      "first_name": "Rosy",
      "last_name": "Vel",
      "phone": "118-267-3685",
      "email": "rvel3@arstechnica.com",
      "password": "UKhpV9v",
      "active": true
    },
    {
      "id": 5,
      "first_name": "Sargent",
      "last_name": "Annatt",
      "phone": "336-295-8015",
      "email": "sannatt4@nifty.com",
      "password": "U7AqBNvS3F4P",
      "active": true
    },
    {
      "id": 6,
      "first_name": "Annette",
      "last_name": "Eveque",
      "phone": "219-729-6197",
      "email": "aeveque5@odnoklassniki.ru",
      "password": "wUV96UNVo9p",
      "active": true
    },
    {
      "id": 7,
      "first_name": "Lucretia",
      "last_name": "Quelch",
      "phone": "332-194-3230",
      "email": "lquelch6@wikipedia.org",
      "password": "n4WzZ8",
      "active": false
    },
    {
      "id": 8,
      "first_name": "Annecorinne",
      "last_name": "Le Barr",
      "phone": "595-338-1063",
      "email": "alebarr7@google.com",
      "password": "jfgSeAOZmkT7",
      "active": true
    },
    {
      "id": 9,
      "first_name": "Tirrell",
      "last_name": "Proschke",
      "phone": "788-621-1528",
      "email": "tproschke8@arizona.edu",
      "password": "9Q7HNzxv",
      "active": true
    },
    {
      "id": 10,
      "first_name": "Seka",
      "last_name": "Thomelin",
      "phone": "351-530-7251",
      "email": "sthomelin9@reverbnation.com",
      "password": "adQr39",
      "active": true
    }
  ]